{
    "type": "Feature",
    "stac_version": "1.0.0",
    "id": "S2A_T50XML_20240319T061630_L2A",
    "properties": {
        "created": "2024-03-19T09:42:39.398Z",
        "platform": "sentinel-2a",
        "constellation": "sentinel-2",
        "instruments": [
            "msi"
        ],
        "eo:cloud_cover": 22.571227,
        "proj:epsg": 32650,
        "proj:centroid": {
            "lat": 77.30716,
            "lon": 113.20375
        },
        "mgrs:utm_zone": 50,
        "mgrs:latitude_band": "X",
        "mgrs:grid_square": "ML",
        "grid:code": "MGRS-50XML",
        "view:azimuth": 328.3905894228203,
        "view:incidence_angle": 10.960233230974769,
        "view:sun_azimuth": 208.017625666081,
        "view:sun_elevation": 11.193982719121905,
        "s2:tile_id": "S2A_OPER_MSI_L2A_TL_2APS_20240319T071651_A045648_T50XML_N05.10",
        "s2:degraded_msi_data_percentage": 0,
        "s2:nodata_pixel_percentage": 96.580595,
        "s2:saturated_defective_pixel_percentage": 0,
        "s2:dark_features_percentage": 0,
        "s2:cloud_shadow_percentage": 0,
        "s2:vegetation_percentage": 0,
        "s2:not_vegetated_percentage": 0,
        "s2:water_percentage": 77.42877,
        "s2:unclassified_percentage": 0,
        "s2:medium_proba_clouds_percentage": 20.669252,
        "s2:high_proba_clouds_percentage": 0.083737,
        "s2:thin_cirrus_percentage": 1.818238,
        "s2:snow_ice_percentage": 0,
        "s2:product_type": "S2MSI2A",
        "s2:processing_baseline": "05.10",
        "s2:product_uri": "S2A_MSIL2A_20240319T061631_N0510_R034_T50XML_20240319T071651.SAFE",
        "s2:generation_time": "2024-03-19T07:16:51.000000Z",
        "s2:datatake_id": "GS2A_20240319T061631_045648_N05.10",
        "s2:datatake_type": "INS-NOBS",
        "s2:datastrip_id": "S2A_OPER_MSI_L2A_DS_2APS_20240319T071651_S20240319T061630_N05.10",
        "s2:reflectance_conversion_factor": 1.01131066413009,
        "datetime": "2024-03-19T06:16:34.753000Z",
        "earthsearch:payload_id": "roda-sentinel-2-c1-l2a/workflow-sentinel-2-c1-l2a-to-stac/db49fbf8eaba53986c77edb942db6100",
        "storage:platform": "AWS",
        "storage:region": "us-west-2",
        "storage:requester_pays": false,
        "processing:software": {
            "sentinel-2-c1-l2a-to-stac": "v2024.02.01"
        },
        "updated": "2024-03-19T09:42:39.398Z"
    },
    "geometry": {
        "type": "Polygon",
        "coordinates": [
            [
                [
                    112.96986768555715,
                    77.14230405913031
                ],
                [
                    113.73091651350498,
                    77.27956604792664
                ],
                [
                    113.1729693809282,
                    77.44895288963393
                ],
                [
                    112.87421933613196,
                    77.44490222279566
                ],
                [
                    112.96986768555715,
                    77.14230405913031
                ]
            ]
        ]
    },
    "links": [
        {
            "rel": "self",
            "type": "application/geo+json",
            "href": "https://dev.eodatahub.org.uk/catalogue-data/element84-data/collections/sentinel-2-c1-l2a/items/S2A_T50XML_20240319T061630_L2A.json"
        },
        {
            "rel": "canonical",
            "href": "s3:/e84-earth-search-sentinel-data/sentinel-2-c1-l2a/50/X/ML/2024/3/S2A_T50XML_20240319T061630_L2A/S2A_T50XML_20240319T061630_L2A.json",
            "type": "application/json"
        },
        {
            "rel": "via",
            "href": "s3:/sentinel-s2-l2a/tiles/50/X/ML/2024/3/19/1/metadata.xml",
            "type": "application/xml",
            "title": "Granule Metadata in Sinergize RODA Archive"
        },
        {
            "rel": "parent",
            "type": "application/json",
            "href": "https://dev.eodatahub.org.uk/catalogue-data/element84-data/collections/sentinel-2-c1-l2a.json"
        },
        {
            "rel": "collection",
            "type": "application/json",
            "href": "https://dev.eodatahub.org.uk/catalogue-data/element84-data/collections/sentinel-2-c1-l2a.json"
        },
        {
            "rel": "root",
            "type": "application/json",
            "href": "https://dev.eodatahub.org.uk/catalogue-data/element84-data/catalog.json"
        },
        {
            "rel": "thumbnail",
            "href": "https://earth-search.aws.element84.com/v1/collections/sentinel-2-c1-l2a/items/S2A_T50XML_20240319T061630_L2A/thumbnail"
        }
    ],
    "assets": {
        "red": {
            "href": "https://e84-earth-search-sentinel-data.s3.us-west-2.amazonaws.com/sentinel-2-c1-l2a/50/X/ML/2024/3/S2A_T50XML_20240319T061630_L2A/B04.tif",
            "type": "image/tiff; application=geotiff; profile=cloud-optimized",
            "title": "Red - 10m",
            "eo:bands": [
                {
                    "name": "B04",
                    "common_name": "red",
                    "center_wavelength": 0.665,
                    "full_width_half_max": 0.038
                }
            ],
            "gsd": 10,
            "proj:shape": [
                10980,
                10980
            ],
            "proj:transform": [
                10,
                0,
                399960,
                0,
                -10,
                8600040
            ],
            "raster:bands": [
                {
                    "nodata": 0,
                    "data_type": "uint16",
                    "spatial_resolution": 10,
                    "scale": 0.0001,
                    "offset": -0.1
                }
            ],
            "file:checksum": "1220880004c560b49213204e1c72fe90a7bde6fe71c1570472a47ff914294238ebe7",
            "file:size": 6478478,
            "roles": [
                "data",
                "reflectance"
            ]
        },
        "green": {
            "href": "https://e84-earth-search-sentinel-data.s3.us-west-2.amazonaws.com/sentinel-2-c1-l2a/50/X/ML/2024/3/S2A_T50XML_20240319T061630_L2A/B03.tif",
            "type": "image/tiff; application=geotiff; profile=cloud-optimized",
            "title": "Green - 10m",
            "eo:bands": [
                {
                    "name": "B03",
                    "common_name": "green",
                    "center_wavelength": 0.56,
                    "full_width_half_max": 0.045
                }
            ],
            "gsd": 10,
            "proj:shape": [
                10980,
                10980
            ],
            "proj:transform": [
                10,
                0,
                399960,
                0,
                -10,
                8600040
            ],
            "raster:bands": [
                {
                    "nodata": 0,
                    "data_type": "uint16",
                    "spatial_resolution": 10,
                    "scale": 0.0001,
                    "offset": -0.1
                }
            ],
            "file:checksum": "1220a18943c8a6629968a347b5fd9c81e29277f4f82854ec741e54992e832a1b4389",
            "file:size": 6463116,
            "roles": [
                "data",
                "reflectance"
            ]
        },
        "blue": {
            "href": "https://e84-earth-search-sentinel-data.s3.us-west-2.amazonaws.com/sentinel-2-c1-l2a/50/X/ML/2024/3/S2A_T50XML_20240319T061630_L2A/B02.tif",
            "type": "image/tiff; application=geotiff; profile=cloud-optimized",
            "title": "Blue - 10m",
            "eo:bands": [
                {
                    "name": "B02",
                    "common_name": "blue",
                    "center_wavelength": 0.49,
                    "full_width_half_max": 0.098
                }
            ],
            "gsd": 10,
            "proj:shape": [
                10980,
                10980
            ],
            "proj:transform": [
                10,
                0,
                399960,
                0,
                -10,
                8600040
            ],
            "raster:bands": [
                {
                    "nodata": 0,
                    "data_type": "uint16",
                    "spatial_resolution": 10,
                    "scale": 0.0001,
                    "offset": -0.1
                }
            ],
            "file:checksum": "1220f059846d17a8a3d923f2c1e766c871505f61f3e03657e3861951e8a7d539e1fa",
            "file:size": 6490681,
            "roles": [
                "data",
                "reflectance"
            ]
        },
        "visual": {
            "href": "https://e84-earth-search-sentinel-data.s3.us-west-2.amazonaws.com/sentinel-2-c1-l2a/50/X/ML/2024/3/S2A_T50XML_20240319T061630_L2A/TCI.tif",
            "type": "image/tiff; application=geotiff; profile=cloud-optimized",
            "title": "True color image",
            "eo:bands": [
                {
                    "name": "B04",
                    "common_name": "red",
                    "center_wavelength": 0.665,
                    "full_width_half_max": 0.038
                },
                {
                    "name": "B03",
                    "common_name": "green",
                    "center_wavelength": 0.56,
                    "full_width_half_max": 0.045
                },
                {
                    "name": "B02",
                    "common_name": "blue",
                    "center_wavelength": 0.49,
                    "full_width_half_max": 0.098
                }
            ],
            "gsd": 10,
            "proj:shape": [
                10980,
                10980
            ],
            "proj:transform": [
                10,
                0,
                399960,
                0,
                -10,
                8600040
            ],
            "file:checksum": "1220f7a1d0f3a6142cb228be545312d4b43d230d7b511016e491929d8de64a095281",
            "file:size": 541324,
            "roles": [
                "visual"
            ]
        },
        "nir": {
            "href": "https://e84-earth-search-sentinel-data.s3.us-west-2.amazonaws.com/sentinel-2-c1-l2a/50/X/ML/2024/3/S2A_T50XML_20240319T061630_L2A/B08.tif",
            "type": "image/tiff; application=geotiff; profile=cloud-optimized",
            "title": "NIR 1 - 10m",
            "eo:bands": [
                {
                    "name": "B08",
                    "common_name": "nir",
                    "center_wavelength": 0.842,
                    "full_width_half_max": 0.145
                }
            ],
            "gsd": 10,
            "proj:shape": [
                10980,
                10980
            ],
            "proj:transform": [
                10,
                0,
                399960,
                0,
                -10,
                8600040
            ],
            "raster:bands": [
                {
                    "nodata": 0,
                    "data_type": "uint16",
                    "spatial_resolution": 10,
                    "scale": 0.0001,
                    "offset": -0.1
                }
            ],
            "file:checksum": "12206e8d854386e426e04cc96f4cd4c0be03bf5983a7b920697935fbdbda6d02bb6e",
            "file:size": 6671562,
            "roles": [
                "data",
                "reflectance"
            ]
        },
        "swir22": {
            "href": "https://e84-earth-search-sentinel-data.s3.us-west-2.amazonaws.com/sentinel-2-c1-l2a/50/X/ML/2024/3/S2A_T50XML_20240319T061630_L2A/B12.tif",
            "type": "image/tiff; application=geotiff; profile=cloud-optimized",
            "title": "SWIR 2.2\u03bcm - 20m",
            "eo:bands": [
                {
                    "name": "B12",
                    "common_name": "swir22",
                    "center_wavelength": 2.19,
                    "full_width_half_max": 0.242
                }
            ],
            "gsd": 20,
            "proj:shape": [
                5490,
                5490
            ],
            "proj:transform": [
                20,
                0,
                399960,
                0,
                -20,
                8600040
            ],
            "raster:bands": [
                {
                    "nodata": 0,
                    "data_type": "uint16",
                    "spatial_resolution": 20,
                    "scale": 0.0001,
                    "offset": -0.1
                }
            ],
            "file:checksum": "122034a86481adb5689973a4219ee9fcf555764506f8247269af9cc37b2d80acd0af",
            "file:size": 1758883,
            "roles": [
                "data",
                "reflectance"
            ]
        },
        "rededge2": {
            "href": "https://e84-earth-search-sentinel-data.s3.us-west-2.amazonaws.com/sentinel-2-c1-l2a/50/X/ML/2024/3/S2A_T50XML_20240319T061630_L2A/B06.tif",
            "type": "image/tiff; application=geotiff; profile=cloud-optimized",
            "title": "Red Edge 2 - 20m",
            "eo:bands": [
                {
                    "name": "B06",
                    "common_name": "rededge",
                    "center_wavelength": 0.74,
                    "full_width_half_max": 0.018
                }
            ],
            "gsd": 20,
            "proj:shape": [
                5490,
                5490
            ],
            "proj:transform": [
                20,
                0,
                399960,
                0,
                -20,
                8600040
            ],
            "raster:bands": [
                {
                    "nodata": 0,
                    "data_type": "uint16",
                    "spatial_resolution": 20,
                    "scale": 0.0001,
                    "offset": -0.1
                }
            ],
            "file:checksum": "1220b41603671cf9b4c0fcdfdc01e2013a530c73f234cb88edc3c6424522073fd7ed",
            "file:size": 2038977,
            "roles": [
                "data",
                "reflectance"
            ]
        },
        "rededge3": {
            "href": "https://e84-earth-search-sentinel-data.s3.us-west-2.amazonaws.com/sentinel-2-c1-l2a/50/X/ML/2024/3/S2A_T50XML_20240319T061630_L2A/B07.tif",
            "type": "image/tiff; application=geotiff; profile=cloud-optimized",
            "title": "Red Edge 3 - 20m",
            "eo:bands": [
                {
                    "name": "B07",
                    "common_name": "rededge",
                    "center_wavelength": 0.783,
                    "full_width_half_max": 0.028
                }
            ],
            "gsd": 20,
            "proj:shape": [
                5490,
                5490
            ],
            "proj:transform": [
                20,
                0,
                399960,
                0,
                -20,
                8600040
            ],
            "raster:bands": [
                {
                    "nodata": 0,
                    "data_type": "uint16",
                    "spatial_resolution": 20,
                    "scale": 0.0001,
                    "offset": -0.1
                }
            ],
            "file:checksum": "12202aa83f00ae1f3883be71e53b5b8feb8ed4a83302d1d7035450983f481b5d3fa4",
            "file:size": 2049218,
            "roles": [
                "data",
                "reflectance"
            ]
        },
        "rededge1": {
            "href": "https://e84-earth-search-sentinel-data.s3.us-west-2.amazonaws.com/sentinel-2-c1-l2a/50/X/ML/2024/3/S2A_T50XML_20240319T061630_L2A/B05.tif",
            "type": "image/tiff; application=geotiff; profile=cloud-optimized",
            "title": "Red Edge 1 - 20m",
            "eo:bands": [
                {
                    "name": "B05",
                    "common_name": "rededge",
                    "center_wavelength": 0.704,
                    "full_width_half_max": 0.019
                }
            ],
            "gsd": 20,
            "proj:shape": [
                5490,
                5490
            ],
            "proj:transform": [
                20,
                0,
                399960,
                0,
                -20,
                8600040
            ],
            "raster:bands": [
                {
                    "nodata": 0,
                    "data_type": "uint16",
                    "spatial_resolution": 20,
                    "scale": 0.0001,
                    "offset": -0.1
                }
            ],
            "file:checksum": "12202efeaef1a431d7e5ed1117b7561e9558f69b330e1fb4e833b52440469df4cad1",
            "file:size": 2017950,
            "roles": [
                "data",
                "reflectance"
            ]
        },
        "swir16": {
            "href": "https://e84-earth-search-sentinel-data.s3.us-west-2.amazonaws.com/sentinel-2-c1-l2a/50/X/ML/2024/3/S2A_T50XML_20240319T061630_L2A/B11.tif",
            "type": "image/tiff; application=geotiff; profile=cloud-optimized",
            "title": "SWIR 1.6\u03bcm - 20m",
            "eo:bands": [
                {
                    "name": "B11",
                    "common_name": "swir16",
                    "center_wavelength": 1.61,
                    "full_width_half_max": 0.143
                }
            ],
            "gsd": 20,
            "proj:shape": [
                5490,
                5490
            ],
            "proj:transform": [
                20,
                0,
                399960,
                0,
                -20,
                8600040
            ],
            "raster:bands": [
                {
                    "nodata": 0,
                    "data_type": "uint16",
                    "spatial_resolution": 20,
                    "scale": 0.0001,
                    "offset": -0.1
                }
            ],
            "file:checksum": "1220db00151405d9199b66aff88a0306b1f4c66d2f46fc0552beff8bc17cd5d432ad",
            "file:size": 1743002,
            "roles": [
                "data",
                "reflectance"
            ]
        },
        "wvp": {
            "href": "https://e84-earth-search-sentinel-data.s3.us-west-2.amazonaws.com/sentinel-2-c1-l2a/50/X/ML/2024/3/S2A_T50XML_20240319T061630_L2A/WVP.tif",
            "type": "image/tiff; application=geotiff; profile=cloud-optimized",
            "title": "Water Vapour (WVP)",
            "gsd": 20,
            "proj:shape": [
                5490,
                5490
            ],
            "proj:transform": [
                20,
                0,
                399960,
                0,
                -20,
                8600040
            ],
            "raster:bands": [
                {
                    "nodata": 0,
                    "data_type": "uint16",
                    "spatial_resolution": 20,
                    "unit": "cm",
                    "scale": 0.001,
                    "offset": 0
                }
            ],
            "file:checksum": "1220b4699d9e382ce1fc462efa2a711568e7ebef60a4216cff74921ae6aa40d16296",
            "file:size": 95845,
            "roles": [
                "data"
            ]
        },
        "nir08": {
            "href": "https://e84-earth-search-sentinel-data.s3.us-west-2.amazonaws.com/sentinel-2-c1-l2a/50/X/ML/2024/3/S2A_T50XML_20240319T061630_L2A/B8A.tif",
            "type": "image/tiff; application=geotiff; profile=cloud-optimized",
            "title": "NIR 2 - 20m",
            "eo:bands": [
                {
                    "name": "B8A",
                    "common_name": "nir08",
                    "center_wavelength": 0.865,
                    "full_width_half_max": 0.033
                }
            ],
            "gsd": 20,
            "proj:shape": [
                5490,
                5490
            ],
            "proj:transform": [
                20,
                0,
                399960,
                0,
                -20,
                8600040
            ],
            "raster:bands": [
                {
                    "nodata": 0,
                    "data_type": "uint16",
                    "spatial_resolution": 20,
                    "scale": 0.0001,
                    "offset": -0.1
                }
            ],
            "file:checksum": "12209585081deb64299cc530cfec76f85bfb747c35d7671fe66e8fb9c7488dda5f9c",
            "file:size": 2087006,
            "roles": [
                "data",
                "reflectance"
            ]
        },
        "scl": {
            "href": "https://e84-earth-search-sentinel-data.s3.us-west-2.amazonaws.com/sentinel-2-c1-l2a/50/X/ML/2024/3/S2A_T50XML_20240319T061630_L2A/SCL.tif",
            "type": "image/tiff; application=geotiff; profile=cloud-optimized",
            "title": "Scene classification map (SCL)",
            "gsd": 20,
            "proj:shape": [
                5490,
                5490
            ],
            "proj:transform": [
                20,
                0,
                399960,
                0,
                -20,
                8600040
            ],
            "raster:bands": [
                {
                    "nodata": 0,
                    "data_type": "uint8",
                    "spatial_resolution": 20
                }
            ],
            "file:checksum": "1220866e88d6c6b8b912abe39a9173fc01aa9478c93136b497fadfc802ff822bf5c9",
            "file:size": 119831,
            "roles": [
                "data"
            ]
        },
        "aot": {
            "href": "https://e84-earth-search-sentinel-data.s3.us-west-2.amazonaws.com/sentinel-2-c1-l2a/50/X/ML/2024/3/S2A_T50XML_20240319T061630_L2A/AOT.tif",
            "type": "image/tiff; application=geotiff; profile=cloud-optimized",
            "title": "Aerosol optical thickness (AOT)",
            "gsd": 20,
            "proj:shape": [
                5490,
                5490
            ],
            "proj:transform": [
                20,
                0,
                399960,
                0,
                -20,
                8600040
            ],
            "raster:bands": [
                {
                    "nodata": 0,
                    "data_type": "uint16",
                    "spatial_resolution": 20,
                    "scale": 0.001,
                    "offset": 0
                }
            ],
            "file:checksum": "122081cce2085722cc785fc54b73fcf357a0731afdf45f4085aa9eed1a06c7c33da4",
            "file:size": 112143,
            "roles": [
                "data"
            ]
        },
        "coastal": {
            "href": "https://e84-earth-search-sentinel-data.s3.us-west-2.amazonaws.com/sentinel-2-c1-l2a/50/X/ML/2024/3/S2A_T50XML_20240319T061630_L2A/B01.tif",
            "type": "image/tiff; application=geotiff; profile=cloud-optimized",
            "title": "Coastal - 60m",
            "eo:bands": [
                {
                    "name": "B01",
                    "common_name": "coastal",
                    "center_wavelength": 0.443,
                    "full_width_half_max": 0.027
                }
            ],
            "gsd": 60,
            "proj:shape": [
                1830,
                1830
            ],
            "proj:transform": [
                60,
                0,
                399960,
                0,
                -60,
                8600040
            ],
            "raster:bands": [
                {
                    "nodata": 0,
                    "data_type": "uint16",
                    "spatial_resolution": 60,
                    "scale": 0.0001,
                    "offset": -0.1
                }
            ],
            "file:checksum": "1220cd10f4c682f74304589c362514501ab8d0d2c091292e00f2b3c4f080e2c1ec70",
            "file:size": 231788,
            "roles": [
                "data",
                "reflectance"
            ]
        },
        "nir09": {
            "href": "https://e84-earth-search-sentinel-data.s3.us-west-2.amazonaws.com/sentinel-2-c1-l2a/50/X/ML/2024/3/S2A_T50XML_20240319T061630_L2A/B09.tif",
            "type": "image/tiff; application=geotiff; profile=cloud-optimized",
            "title": "NIR 3 - 60m",
            "eo:bands": [
                {
                    "name": "B09",
                    "common_name": "nir09",
                    "center_wavelength": 0.945,
                    "full_width_half_max": 0.026
                }
            ],
            "gsd": 60,
            "proj:shape": [
                1830,
                1830
            ],
            "proj:transform": [
                60,
                0,
                399960,
                0,
                -60,
                8600040
            ],
            "raster:bands": [
                {
                    "nodata": 0,
                    "data_type": "uint16",
                    "spatial_resolution": 60,
                    "scale": 0.0001,
                    "offset": -0.1
                }
            ],
            "file:checksum": "1220fcbc1d9ba2747b1c34d8e609c3a816ef21067bb50bcbcdd70fff39aa0eb736c7",
            "file:size": 217669,
            "roles": [
                "data",
                "reflectance"
            ]
        },
        "cloud": {
            "href": "https://e84-earth-search-sentinel-data.s3.us-west-2.amazonaws.com/sentinel-2-c1-l2a/50/X/ML/2024/3/S2A_T50XML_20240319T061630_L2A/CLD_20m.tif",
            "type": "image/tiff; application=geotiff; profile=cloud-optimized",
            "title": "Cloud Probabilities",
            "gsd": 20,
            "proj:shape": [
                5490,
                5490
            ],
            "proj:transform": [
                20,
                0,
                399960,
                0,
                -20,
                8600040
            ],
            "raster:bands": [
                {
                    "nodata": 0,
                    "data_type": "uint8",
                    "spatial_resolution": 20
                }
            ],
            "file:checksum": "1220cd2877ac44989f938661e7b8779a5c8f3e332c774f4dae47de26c22876f38a2a",
            "file:size": 287521,
            "roles": [
                "data",
                "cloud"
            ]
        },
        "snow": {
            "href": "https://e84-earth-search-sentinel-data.s3.us-west-2.amazonaws.com/sentinel-2-c1-l2a/50/X/ML/2024/3/S2A_T50XML_20240319T061630_L2A/SNW_20m.tif",
            "type": "image/tiff; application=geotiff; profile=cloud-optimized",
            "title": "Snow Probabilities",
            "proj:shape": [
                5490,
                5490
            ],
            "proj:transform": [
                20,
                0,
                399960,
                0,
                -20,
                8600040
            ],
            "raster:bands": [
                {
                    "nodata": 0,
                    "data_type": "uint8",
                    "spatial_resolution": 20
                }
            ],
            "file:checksum": "12203c1e25095ee4549cc58f3adafdbb1d08a8d94e8c3053e1d80b8efb4e255907ad",
            "file:size": 53931,
            "roles": [
                "data",
                "snow-ice"
            ]
        },
        "preview": {
            "href": "https://e84-earth-search-sentinel-data.s3.us-west-2.amazonaws.com/sentinel-2-c1-l2a/50/X/ML/2024/3/S2A_T50XML_20240319T061630_L2A/L2A_PVI.tif",
            "type": "image/tiff; application=geotiff; profile=cloud-optimized",
            "title": "True color preview",
            "eo:bands": [
                {
                    "name": "B04",
                    "common_name": "red",
                    "center_wavelength": 0.665,
                    "full_width_half_max": 0.038
                },
                {
                    "name": "B03",
                    "common_name": "green",
                    "center_wavelength": 0.56,
                    "full_width_half_max": 0.045
                },
                {
                    "name": "B02",
                    "common_name": "blue",
                    "center_wavelength": 0.49,
                    "full_width_half_max": 0.098
                }
            ],
            "file:checksum": "12201907bd9c6fad0469195eda6d40519724d00e6e1acd931a50cf80f6001df1d655",
            "file:size": 5088,
            "roles": [
                "overview"
            ]
        },
        "granule_metadata": {
            "href": "https://e84-earth-search-sentinel-data.s3.us-west-2.amazonaws.com/sentinel-2-c1-l2a/50/X/ML/2024/3/S2A_T50XML_20240319T061630_L2A/metadata.xml",
            "type": "application/xml",
            "file:checksum": "122043536f0f53b1c201507f0eef36997a9d9ecac8bd69b35cdc71dead5883d73fa4",
            "file:size": 180318,
            "roles": [
                "metadata"
            ]
        },
        "tileinfo_metadata": {
            "href": "https://e84-earth-search-sentinel-data.s3.us-west-2.amazonaws.com/sentinel-2-c1-l2a/50/X/ML/2024/3/S2A_T50XML_20240319T061630_L2A/tileInfo.json",
            "type": "application/json",
            "file:checksum": "1220abeab1591533428203a0899bc33ca2914becf35f73950d919b22384e4f5b7f24",
            "file:size": 1548,
            "roles": [
                "metadata"
            ]
        },
        "product_metadata": {
            "href": "https://e84-earth-search-sentinel-data.s3.us-west-2.amazonaws.com/sentinel-2-c1-l2a/50/X/ML/2024/3/S2A_T50XML_20240319T061630_L2A/product_metadata.xml",
            "type": "application/xml",
            "file:checksum": "12206d47cc1094718d86763c74fc4ca444d1705ddd09a2b32a3f6bd8d6cb0c2ed747",
            "file:size": 54483,
            "roles": [
                "metadata"
            ]
        },
        "thumbnail": {
            "href": "https://e84-earth-search-sentinel-data.s3.us-west-2.amazonaws.com/sentinel-2-c1-l2a/50/X/ML/2024/3/S2A_T50XML_20240319T061630_L2A/L2A_PVI.jpg",
            "type": "image/jpeg",
            "title": "Thumbnail of preview image",
            "file:checksum": "12200031940eb4e0d5e837ef3ad34c259a7d4a99f2f9502f1c81f063d5ae15273bef",
            "file:size": 3312,
            "roles": [
                "thumbnail"
            ]
        }
    },
    "bbox": [
        112.874219,
        77.142304,
        113.730917,
        77.448953
    ],
    "stac_extensions": [
        "https://stac-extensions.github.io/eo/v1.1.0/schema.json",
        "https://stac-extensions.github.io/file/v2.1.0/schema.json",
        "https://stac-extensions.github.io/grid/v1.1.0/schema.json",
        "https://stac-extensions.github.io/mgrs/v1.0.0/schema.json",
        "https://stac-extensions.github.io/processing/v1.1.0/schema.json",
        "https://stac-extensions.github.io/projection/v1.1.0/schema.json",
        "https://stac-extensions.github.io/raster/v1.1.0/schema.json",
        "https://stac-extensions.github.io/sentinel-2/v1.0.0/schema.json",
        "https://stac-extensions.github.io/storage/v1.0.0/schema.json",
        "https://stac-extensions.github.io/view/v1.0.0/schema.json"
    ],
    "collection": "sentinel-2-c1-l2a"
}