{
    "type": "Feature",
    "stac_version": "1.0.0",
    "id": "S2B_T43NBE_20240319T054135_L2A",
    "properties": {
        "created": "2024-03-19T09:42:01.812Z",
        "platform": "sentinel-2b",
        "constellation": "sentinel-2",
        "instruments": [
            "msi"
        ],
        "eo:cloud_cover": 0.912306,
        "proj:epsg": 32643,
        "proj:centroid": {
            "lat": 4.12161,
            "lon": 72.4032
        },
        "mgrs:utm_zone": 43,
        "mgrs:latitude_band": "N",
        "mgrs:grid_square": "BE",
        "grid:code": "MGRS-43NBE",
        "view:azimuth": 288.9606224473293,
        "view:incidence_angle": 10.906961495119115,
        "view:sun_azimuth": 100.668895992312,
        "view:sun_elevation": 67.4310101174639,
        "s2:tile_id": "S2B_OPER_MSI_L2A_TL_2BPS_20240319T075439_A036739_T43NBE_N05.10",
        "s2:degraded_msi_data_percentage": 0,
        "s2:nodata_pixel_percentage": 80.821908,
        "s2:saturated_defective_pixel_percentage": 0,
        "s2:dark_features_percentage": 0,
        "s2:cloud_shadow_percentage": 0,
        "s2:vegetation_percentage": 0,
        "s2:not_vegetated_percentage": 0.027403,
        "s2:water_percentage": 99.060291,
        "s2:unclassified_percentage": 0,
        "s2:medium_proba_clouds_percentage": 0.737782,
        "s2:high_proba_clouds_percentage": 0.174524,
        "s2:thin_cirrus_percentage": 0,
        "s2:snow_ice_percentage": 0,
        "s2:product_type": "S2MSI2A",
        "s2:processing_baseline": "05.10",
        "s2:product_uri": "S2B_MSIL2A_20240319T052649_N0510_R105_T43NBE_20240319T075439.SAFE",
        "s2:generation_time": "2024-03-19T07:54:39.000000Z",
        "s2:datatake_id": "GS2B_20240319T052649_036739_N05.10",
        "s2:datatake_type": "INS-NOBS",
        "s2:datastrip_id": "S2B_OPER_MSI_L2A_DS_2BPS_20240319T075439_S20240319T054135_N05.10",
        "s2:reflectance_conversion_factor": 1.01132969483839,
        "datetime": "2024-03-19T05:47:49.731000Z",
        "earthsearch:payload_id": "roda-sentinel-2-c1-l2a/workflow-sentinel-2-c1-l2a-to-stac/0c905294727eee05b5c3f86b9f6c00eb",
        "storage:platform": "AWS",
        "storage:region": "us-west-2",
        "storage:requester_pays": false,
        "processing:software": {
            "sentinel-2-c1-l2a-to-stac": "v2024.02.01"
        },
        "updated": "2024-03-19T09:42:01.812Z"
    },
    "geometry": {
        "type": "Polygon",
        "coordinates": [
            [
                [
                    72.29645178970969,
                    4.518867351812951
                ],
                [
                    72.29972038292655,
                    3.527555390768976
                ],
                [
                    72.3770408818292,
                    3.5293420459878253
                ],
                [
                    72.59701469786332,
                    4.5199272335291925
                ],
                [
                    72.29645178970969,
                    4.518867351812951
                ]
            ]
        ]
    },
    "links": [
        {
            "rel": "self",
            "type": "application/geo+json",
            "href": "https://dev.eodatahub.org.uk/catalogue-data/element84-data/collections/sentinel-2-c1-l2a/items/S2B_T43NBE_20240319T054135_L2A.json"
        },
        {
            "rel": "canonical",
            "href": "s3:/e84-earth-search-sentinel-data/sentinel-2-c1-l2a/43/N/BE/2024/3/S2B_T43NBE_20240319T054135_L2A/S2B_T43NBE_20240319T054135_L2A.json",
            "type": "application/json"
        },
        {
            "rel": "via",
            "href": "s3:/sentinel-s2-l2a/tiles/43/N/BE/2024/3/19/0/metadata.xml",
            "type": "application/xml",
            "title": "Granule Metadata in Sinergize RODA Archive"
        },
        {
            "rel": "parent",
            "type": "application/json",
            "href": "https://dev.eodatahub.org.uk/catalogue-data/element84-data/collections/sentinel-2-c1-l2a.json"
        },
        {
            "rel": "collection",
            "type": "application/json",
            "href": "https://dev.eodatahub.org.uk/catalogue-data/element84-data/collections/sentinel-2-c1-l2a.json"
        },
        {
            "rel": "root",
            "type": "application/json",
            "href": "https://dev.eodatahub.org.uk/catalogue-data/element84-data/catalog.json"
        },
        {
            "rel": "thumbnail",
            "href": "https://earth-search.aws.element84.com/v1/collections/sentinel-2-c1-l2a/items/S2B_T43NBE_20240319T054135_L2A/thumbnail"
        }
    ],
    "assets": {
        "red": {
            "href": "https://e84-earth-search-sentinel-data.s3.us-west-2.amazonaws.com/sentinel-2-c1-l2a/43/N/BE/2024/3/S2B_T43NBE_20240319T054135_L2A/B04.tif",
            "type": "image/tiff; application=geotiff; profile=cloud-optimized",
            "title": "Red - 10m",
            "eo:bands": [
                {
                    "name": "B04",
                    "common_name": "red",
                    "center_wavelength": 0.665,
                    "full_width_half_max": 0.038
                }
            ],
            "gsd": 10,
            "proj:shape": [
                10980,
                10980
            ],
            "proj:transform": [
                10,
                0,
                199980,
                0,
                -10,
                500040
            ],
            "raster:bands": [
                {
                    "nodata": 0,
                    "data_type": "uint16",
                    "spatial_resolution": 10,
                    "scale": 0.0001,
                    "offset": -0.1
                }
            ],
            "file:checksum": "1220ec4800b38cffcafd9262cb5a154a35c610fd2dd140902edfa0ec2955467c7d2f",
            "file:size": 37677983,
            "roles": [
                "data",
                "reflectance"
            ]
        },
        "green": {
            "href": "https://e84-earth-search-sentinel-data.s3.us-west-2.amazonaws.com/sentinel-2-c1-l2a/43/N/BE/2024/3/S2B_T43NBE_20240319T054135_L2A/B03.tif",
            "type": "image/tiff; application=geotiff; profile=cloud-optimized",
            "title": "Green - 10m",
            "eo:bands": [
                {
                    "name": "B03",
                    "common_name": "green",
                    "center_wavelength": 0.56,
                    "full_width_half_max": 0.045
                }
            ],
            "gsd": 10,
            "proj:shape": [
                10980,
                10980
            ],
            "proj:transform": [
                10,
                0,
                199980,
                0,
                -10,
                500040
            ],
            "raster:bands": [
                {
                    "nodata": 0,
                    "data_type": "uint16",
                    "spatial_resolution": 10,
                    "scale": 0.0001,
                    "offset": -0.1
                }
            ],
            "file:checksum": "122047a663d959802c28539a44f8063aa817f4d18b544a6835d95cff76cb506822b2",
            "file:size": 38022324,
            "roles": [
                "data",
                "reflectance"
            ]
        },
        "blue": {
            "href": "https://e84-earth-search-sentinel-data.s3.us-west-2.amazonaws.com/sentinel-2-c1-l2a/43/N/BE/2024/3/S2B_T43NBE_20240319T054135_L2A/B02.tif",
            "type": "image/tiff; application=geotiff; profile=cloud-optimized",
            "title": "Blue - 10m",
            "eo:bands": [
                {
                    "name": "B02",
                    "common_name": "blue",
                    "center_wavelength": 0.49,
                    "full_width_half_max": 0.098
                }
            ],
            "gsd": 10,
            "proj:shape": [
                10980,
                10980
            ],
            "proj:transform": [
                10,
                0,
                199980,
                0,
                -10,
                500040
            ],
            "raster:bands": [
                {
                    "nodata": 0,
                    "data_type": "uint16",
                    "spatial_resolution": 10,
                    "scale": 0.0001,
                    "offset": -0.1
                }
            ],
            "file:checksum": "1220816eae9e331e8699c787295ceeb1b7616ebafb3e1a6c947870c19f2c88e78b3f",
            "file:size": 36724676,
            "roles": [
                "data",
                "reflectance"
            ]
        },
        "visual": {
            "href": "https://e84-earth-search-sentinel-data.s3.us-west-2.amazonaws.com/sentinel-2-c1-l2a/43/N/BE/2024/3/S2B_T43NBE_20240319T054135_L2A/TCI.tif",
            "type": "image/tiff; application=geotiff; profile=cloud-optimized",
            "title": "True color image",
            "eo:bands": [
                {
                    "name": "B04",
                    "common_name": "red",
                    "center_wavelength": 0.665,
                    "full_width_half_max": 0.038
                },
                {
                    "name": "B03",
                    "common_name": "green",
                    "center_wavelength": 0.56,
                    "full_width_half_max": 0.045
                },
                {
                    "name": "B02",
                    "common_name": "blue",
                    "center_wavelength": 0.49,
                    "full_width_half_max": 0.098
                }
            ],
            "gsd": 10,
            "proj:shape": [
                10980,
                10980
            ],
            "proj:transform": [
                10,
                0,
                199980,
                0,
                -10,
                500040
            ],
            "file:checksum": "122004f504b517afd7b0d882d2218b55394c7b9352fa3b35525114b4ee6de4f78eb9",
            "file:size": 57951458,
            "roles": [
                "visual"
            ]
        },
        "nir": {
            "href": "https://e84-earth-search-sentinel-data.s3.us-west-2.amazonaws.com/sentinel-2-c1-l2a/43/N/BE/2024/3/S2B_T43NBE_20240319T054135_L2A/B08.tif",
            "type": "image/tiff; application=geotiff; profile=cloud-optimized",
            "title": "NIR 1 - 10m",
            "eo:bands": [
                {
                    "name": "B08",
                    "common_name": "nir",
                    "center_wavelength": 0.842,
                    "full_width_half_max": 0.145
                }
            ],
            "gsd": 10,
            "proj:shape": [
                10980,
                10980
            ],
            "proj:transform": [
                10,
                0,
                199980,
                0,
                -10,
                500040
            ],
            "raster:bands": [
                {
                    "nodata": 0,
                    "data_type": "uint16",
                    "spatial_resolution": 10,
                    "scale": 0.0001,
                    "offset": -0.1
                }
            ],
            "file:checksum": "1220abe66c9d9ce535867dd61f9726a1840669bbe67654bbbaf40b8ea88963b7fed9",
            "file:size": 37621790,
            "roles": [
                "data",
                "reflectance"
            ]
        },
        "swir22": {
            "href": "https://e84-earth-search-sentinel-data.s3.us-west-2.amazonaws.com/sentinel-2-c1-l2a/43/N/BE/2024/3/S2B_T43NBE_20240319T054135_L2A/B12.tif",
            "type": "image/tiff; application=geotiff; profile=cloud-optimized",
            "title": "SWIR 2.2\u03bcm - 20m",
            "eo:bands": [
                {
                    "name": "B12",
                    "common_name": "swir22",
                    "center_wavelength": 2.19,
                    "full_width_half_max": 0.242
                }
            ],
            "gsd": 20,
            "proj:shape": [
                5490,
                5490
            ],
            "proj:transform": [
                20,
                0,
                199980,
                0,
                -20,
                500040
            ],
            "raster:bands": [
                {
                    "nodata": 0,
                    "data_type": "uint16",
                    "spatial_resolution": 20,
                    "scale": 0.0001,
                    "offset": -0.1
                }
            ],
            "file:checksum": "12208044b9eaac2d59fac849a6e5015f01e91c28812d57ede35bb5d0a6c6fc50d259",
            "file:size": 9086006,
            "roles": [
                "data",
                "reflectance"
            ]
        },
        "rededge2": {
            "href": "https://e84-earth-search-sentinel-data.s3.us-west-2.amazonaws.com/sentinel-2-c1-l2a/43/N/BE/2024/3/S2B_T43NBE_20240319T054135_L2A/B06.tif",
            "type": "image/tiff; application=geotiff; profile=cloud-optimized",
            "title": "Red Edge 2 - 20m",
            "eo:bands": [
                {
                    "name": "B06",
                    "common_name": "rededge",
                    "center_wavelength": 0.74,
                    "full_width_half_max": 0.018
                }
            ],
            "gsd": 20,
            "proj:shape": [
                5490,
                5490
            ],
            "proj:transform": [
                20,
                0,
                199980,
                0,
                -20,
                500040
            ],
            "raster:bands": [
                {
                    "nodata": 0,
                    "data_type": "uint16",
                    "spatial_resolution": 20,
                    "scale": 0.0001,
                    "offset": -0.1
                }
            ],
            "file:checksum": "12202b2e4a45cedf142036c4c4499c168fe54301f97133adecc52238859417f6b34f",
            "file:size": 9531408,
            "roles": [
                "data",
                "reflectance"
            ]
        },
        "rededge3": {
            "href": "https://e84-earth-search-sentinel-data.s3.us-west-2.amazonaws.com/sentinel-2-c1-l2a/43/N/BE/2024/3/S2B_T43NBE_20240319T054135_L2A/B07.tif",
            "type": "image/tiff; application=geotiff; profile=cloud-optimized",
            "title": "Red Edge 3 - 20m",
            "eo:bands": [
                {
                    "name": "B07",
                    "common_name": "rededge",
                    "center_wavelength": 0.783,
                    "full_width_half_max": 0.028
                }
            ],
            "gsd": 20,
            "proj:shape": [
                5490,
                5490
            ],
            "proj:transform": [
                20,
                0,
                199980,
                0,
                -20,
                500040
            ],
            "raster:bands": [
                {
                    "nodata": 0,
                    "data_type": "uint16",
                    "spatial_resolution": 20,
                    "scale": 0.0001,
                    "offset": -0.1
                }
            ],
            "file:checksum": "1220482f604669e921dc8cebde205c8362a0220185e4af94ffd60e30a8c74d062da6",
            "file:size": 9550754,
            "roles": [
                "data",
                "reflectance"
            ]
        },
        "rededge1": {
            "href": "https://e84-earth-search-sentinel-data.s3.us-west-2.amazonaws.com/sentinel-2-c1-l2a/43/N/BE/2024/3/S2B_T43NBE_20240319T054135_L2A/B05.tif",
            "type": "image/tiff; application=geotiff; profile=cloud-optimized",
            "title": "Red Edge 1 - 20m",
            "eo:bands": [
                {
                    "name": "B05",
                    "common_name": "rededge",
                    "center_wavelength": 0.704,
                    "full_width_half_max": 0.019
                }
            ],
            "gsd": 20,
            "proj:shape": [
                5490,
                5490
            ],
            "proj:transform": [
                20,
                0,
                199980,
                0,
                -20,
                500040
            ],
            "raster:bands": [
                {
                    "nodata": 0,
                    "data_type": "uint16",
                    "spatial_resolution": 20,
                    "scale": 0.0001,
                    "offset": -0.1
                }
            ],
            "file:checksum": "1220569d98bba5d7441d7201a08e504836d756126585bdcfe9efbcf6c6b58de37588",
            "file:size": 9586206,
            "roles": [
                "data",
                "reflectance"
            ]
        },
        "swir16": {
            "href": "https://e84-earth-search-sentinel-data.s3.us-west-2.amazonaws.com/sentinel-2-c1-l2a/43/N/BE/2024/3/S2B_T43NBE_20240319T054135_L2A/B11.tif",
            "type": "image/tiff; application=geotiff; profile=cloud-optimized",
            "title": "SWIR 1.6\u03bcm - 20m",
            "eo:bands": [
                {
                    "name": "B11",
                    "common_name": "swir16",
                    "center_wavelength": 1.61,
                    "full_width_half_max": 0.143
                }
            ],
            "gsd": 20,
            "proj:shape": [
                5490,
                5490
            ],
            "proj:transform": [
                20,
                0,
                199980,
                0,
                -20,
                500040
            ],
            "raster:bands": [
                {
                    "nodata": 0,
                    "data_type": "uint16",
                    "spatial_resolution": 20,
                    "scale": 0.0001,
                    "offset": -0.1
                }
            ],
            "file:checksum": "1220232602f07a04bffe7a0345b96b06616c0117ee576cd2b498464bfd31aa01ae20",
            "file:size": 9176888,
            "roles": [
                "data",
                "reflectance"
            ]
        },
        "wvp": {
            "href": "https://e84-earth-search-sentinel-data.s3.us-west-2.amazonaws.com/sentinel-2-c1-l2a/43/N/BE/2024/3/S2B_T43NBE_20240319T054135_L2A/WVP.tif",
            "type": "image/tiff; application=geotiff; profile=cloud-optimized",
            "title": "Water Vapour (WVP)",
            "gsd": 20,
            "proj:shape": [
                5490,
                5490
            ],
            "proj:transform": [
                20,
                0,
                199980,
                0,
                -20,
                500040
            ],
            "raster:bands": [
                {
                    "nodata": 0,
                    "data_type": "uint16",
                    "spatial_resolution": 20,
                    "unit": "cm",
                    "scale": 0.001,
                    "offset": 0
                }
            ],
            "file:checksum": "122085420697f015422fd70152e4f8fa796bd2ed0feeb2e46fb05959e8573b850e72",
            "file:size": 141782,
            "roles": [
                "data"
            ]
        },
        "nir08": {
            "href": "https://e84-earth-search-sentinel-data.s3.us-west-2.amazonaws.com/sentinel-2-c1-l2a/43/N/BE/2024/3/S2B_T43NBE_20240319T054135_L2A/B8A.tif",
            "type": "image/tiff; application=geotiff; profile=cloud-optimized",
            "title": "NIR 2 - 20m",
            "eo:bands": [
                {
                    "name": "B8A",
                    "common_name": "nir08",
                    "center_wavelength": 0.865,
                    "full_width_half_max": 0.033
                }
            ],
            "gsd": 20,
            "proj:shape": [
                5490,
                5490
            ],
            "proj:transform": [
                20,
                0,
                199980,
                0,
                -20,
                500040
            ],
            "raster:bands": [
                {
                    "nodata": 0,
                    "data_type": "uint16",
                    "spatial_resolution": 20,
                    "scale": 0.0001,
                    "offset": -0.1
                }
            ],
            "file:checksum": "12209423740295b78e5e2153b4222994a7fe76cc2cc4a14cb7095cfbe265386fe016",
            "file:size": 9543371,
            "roles": [
                "data",
                "reflectance"
            ]
        },
        "scl": {
            "href": "https://e84-earth-search-sentinel-data.s3.us-west-2.amazonaws.com/sentinel-2-c1-l2a/43/N/BE/2024/3/S2B_T43NBE_20240319T054135_L2A/SCL.tif",
            "type": "image/tiff; application=geotiff; profile=cloud-optimized",
            "title": "Scene classification map (SCL)",
            "gsd": 20,
            "proj:shape": [
                5490,
                5490
            ],
            "proj:transform": [
                20,
                0,
                199980,
                0,
                -20,
                500040
            ],
            "raster:bands": [
                {
                    "nodata": 0,
                    "data_type": "uint8",
                    "spatial_resolution": 20
                }
            ],
            "file:checksum": "122089b6eb288960e96f5d82c7998fef161516df3a8c93be8d618ad10454dd66942d",
            "file:size": 115350,
            "roles": [
                "data"
            ]
        },
        "aot": {
            "href": "https://e84-earth-search-sentinel-data.s3.us-west-2.amazonaws.com/sentinel-2-c1-l2a/43/N/BE/2024/3/S2B_T43NBE_20240319T054135_L2A/AOT.tif",
            "type": "image/tiff; application=geotiff; profile=cloud-optimized",
            "title": "Aerosol optical thickness (AOT)",
            "gsd": 20,
            "proj:shape": [
                5490,
                5490
            ],
            "proj:transform": [
                20,
                0,
                199980,
                0,
                -20,
                500040
            ],
            "raster:bands": [
                {
                    "nodata": 0,
                    "data_type": "uint16",
                    "spatial_resolution": 20,
                    "scale": 0.001,
                    "offset": 0
                }
            ],
            "file:checksum": "1220e610f79f8d320ea2eebbd8a75ca83601009c1c96e6c0ed255ff279e707df69ac",
            "file:size": 164909,
            "roles": [
                "data"
            ]
        },
        "coastal": {
            "href": "https://e84-earth-search-sentinel-data.s3.us-west-2.amazonaws.com/sentinel-2-c1-l2a/43/N/BE/2024/3/S2B_T43NBE_20240319T054135_L2A/B01.tif",
            "type": "image/tiff; application=geotiff; profile=cloud-optimized",
            "title": "Coastal - 60m",
            "eo:bands": [
                {
                    "name": "B01",
                    "common_name": "coastal",
                    "center_wavelength": 0.443,
                    "full_width_half_max": 0.027
                }
            ],
            "gsd": 60,
            "proj:shape": [
                1830,
                1830
            ],
            "proj:transform": [
                60,
                0,
                199980,
                0,
                -60,
                500040
            ],
            "raster:bands": [
                {
                    "nodata": 0,
                    "data_type": "uint16",
                    "spatial_resolution": 60,
                    "scale": 0.0001,
                    "offset": -0.1
                }
            ],
            "file:checksum": "122062b2502c90ab6266a5c47c6ca219b410977ca264e6060e474d26b79ed1334051",
            "file:size": 940458,
            "roles": [
                "data",
                "reflectance"
            ]
        },
        "nir09": {
            "href": "https://e84-earth-search-sentinel-data.s3.us-west-2.amazonaws.com/sentinel-2-c1-l2a/43/N/BE/2024/3/S2B_T43NBE_20240319T054135_L2A/B09.tif",
            "type": "image/tiff; application=geotiff; profile=cloud-optimized",
            "title": "NIR 3 - 60m",
            "eo:bands": [
                {
                    "name": "B09",
                    "common_name": "nir09",
                    "center_wavelength": 0.945,
                    "full_width_half_max": 0.026
                }
            ],
            "gsd": 60,
            "proj:shape": [
                1830,
                1830
            ],
            "proj:transform": [
                60,
                0,
                199980,
                0,
                -60,
                500040
            ],
            "raster:bands": [
                {
                    "nodata": 0,
                    "data_type": "uint16",
                    "spatial_resolution": 60,
                    "scale": 0.0001,
                    "offset": -0.1
                }
            ],
            "file:checksum": "122072a0b2f0d4bc3cc8394b8687351cccbe09bd899dee13e8aac6fad3a689da01ca",
            "file:size": 1045550,
            "roles": [
                "data",
                "reflectance"
            ]
        },
        "cloud": {
            "href": "https://e84-earth-search-sentinel-data.s3.us-west-2.amazonaws.com/sentinel-2-c1-l2a/43/N/BE/2024/3/S2B_T43NBE_20240319T054135_L2A/CLD_20m.tif",
            "type": "image/tiff; application=geotiff; profile=cloud-optimized",
            "title": "Cloud Probabilities",
            "gsd": 20,
            "proj:shape": [
                5490,
                5490
            ],
            "proj:transform": [
                20,
                0,
                199980,
                0,
                -20,
                500040
            ],
            "raster:bands": [
                {
                    "nodata": 0,
                    "data_type": "uint8",
                    "spatial_resolution": 20
                }
            ],
            "file:checksum": "1220d3fb5cb1bbbdc4bf8020d0a7bd676f3e6b2b9d24c4fefc4d2de4ec93c5352326",
            "file:size": 123724,
            "roles": [
                "data",
                "cloud"
            ]
        },
        "snow": {
            "href": "https://e84-earth-search-sentinel-data.s3.us-west-2.amazonaws.com/sentinel-2-c1-l2a/43/N/BE/2024/3/S2B_T43NBE_20240319T054135_L2A/SNW_20m.tif",
            "type": "image/tiff; application=geotiff; profile=cloud-optimized",
            "title": "Snow Probabilities",
            "proj:shape": [
                5490,
                5490
            ],
            "proj:transform": [
                20,
                0,
                199980,
                0,
                -20,
                500040
            ],
            "raster:bands": [
                {
                    "nodata": 0,
                    "data_type": "uint8",
                    "spatial_resolution": 20
                }
            ],
            "file:checksum": "1220ab8adc3970b81a3c73d98c185d96f473e74fd6933277575e6d280d088cb0b08e",
            "file:size": 53931,
            "roles": [
                "data",
                "snow-ice"
            ]
        },
        "preview": {
            "href": "https://e84-earth-search-sentinel-data.s3.us-west-2.amazonaws.com/sentinel-2-c1-l2a/43/N/BE/2024/3/S2B_T43NBE_20240319T054135_L2A/L2A_PVI.tif",
            "type": "image/tiff; application=geotiff; profile=cloud-optimized",
            "title": "True color preview",
            "eo:bands": [
                {
                    "name": "B04",
                    "common_name": "red",
                    "center_wavelength": 0.665,
                    "full_width_half_max": 0.038
                },
                {
                    "name": "B03",
                    "common_name": "green",
                    "center_wavelength": 0.56,
                    "full_width_half_max": 0.045
                },
                {
                    "name": "B02",
                    "common_name": "blue",
                    "center_wavelength": 0.49,
                    "full_width_half_max": 0.098
                }
            ],
            "file:checksum": "1220475da56d72325309ab3857e7146cf3cd9d55cccad70f0568d5928ecd61c12093",
            "file:size": 55795,
            "roles": [
                "overview"
            ]
        },
        "granule_metadata": {
            "href": "https://e84-earth-search-sentinel-data.s3.us-west-2.amazonaws.com/sentinel-2-c1-l2a/43/N/BE/2024/3/S2B_T43NBE_20240319T054135_L2A/metadata.xml",
            "type": "application/xml",
            "file:checksum": "1220c9cb956de292fa9d683f1bc2a1887384f633821ae00c7a46c55e20fef15fea87",
            "file:size": 189381,
            "roles": [
                "metadata"
            ]
        },
        "tileinfo_metadata": {
            "href": "https://e84-earth-search-sentinel-data.s3.us-west-2.amazonaws.com/sentinel-2-c1-l2a/43/N/BE/2024/3/S2B_T43NBE_20240319T054135_L2A/tileInfo.json",
            "type": "application/json",
            "file:checksum": "12207e7c4d808af0ec013ed60083af20ce79d11cdc39a12f1b56af676f5806e10304",
            "file:size": 1518,
            "roles": [
                "metadata"
            ]
        },
        "product_metadata": {
            "href": "https://e84-earth-search-sentinel-data.s3.us-west-2.amazonaws.com/sentinel-2-c1-l2a/43/N/BE/2024/3/S2B_T43NBE_20240319T054135_L2A/product_metadata.xml",
            "type": "application/xml",
            "file:checksum": "1220a19ef4b64413d1bf4018de2b7baf55a7d70c3d0048caf72bb018a059b14489e8",
            "file:size": 54881,
            "roles": [
                "metadata"
            ]
        },
        "thumbnail": {
            "href": "https://e84-earth-search-sentinel-data.s3.us-west-2.amazonaws.com/sentinel-2-c1-l2a/43/N/BE/2024/3/S2B_T43NBE_20240319T054135_L2A/L2A_PVI.jpg",
            "type": "image/jpeg",
            "title": "Thumbnail of preview image",
            "file:checksum": "12208677f908d96b026a968aaf9f4e6302756d68c9a6d40fcf904b9375a8adfb0cf3",
            "file:size": 6394,
            "roles": [
                "thumbnail"
            ]
        }
    },
    "bbox": [
        72.296452,
        3.527555,
        72.597015,
        4.519927
    ],
    "stac_extensions": [
        "https://stac-extensions.github.io/eo/v1.1.0/schema.json",
        "https://stac-extensions.github.io/file/v2.1.0/schema.json",
        "https://stac-extensions.github.io/grid/v1.1.0/schema.json",
        "https://stac-extensions.github.io/mgrs/v1.0.0/schema.json",
        "https://stac-extensions.github.io/processing/v1.1.0/schema.json",
        "https://stac-extensions.github.io/projection/v1.1.0/schema.json",
        "https://stac-extensions.github.io/raster/v1.1.0/schema.json",
        "https://stac-extensions.github.io/sentinel-2/v1.0.0/schema.json",
        "https://stac-extensions.github.io/storage/v1.0.0/schema.json",
        "https://stac-extensions.github.io/view/v1.0.0/schema.json"
    ],
    "collection": "sentinel-2-c1-l2a"
}